[
    {
        "path": "404.html",
        "type": "file",
        "md5": "dcc1d354fcae0e955b023b700b59236d"
    },
    {
        "path": "a-bridge-to-the-infinite",
        "type": "directory",
        "md5": false
    },
    {
        "path": "/a-bridge-to-the-infinite/index.html",
        "type": "file",
        "md5": "d0166e081b57b30f34436fe7188c6b7a"
    },
    {
        "path": "a-frameless-photo",
        "type": "directory",
        "md5": false
    },
    {
        "path": "/a-frameless-photo/index.html",
        "type": "file",
        "md5": "2c159742f7f6dd46b68c71250df4ded0"
    },
    {
        "path": "a-greeting",
        "type": "directory",
        "md5": false
    },
    {
        "path": "/a-greeting/index.html",
        "type": "file",
        "md5": "5584ec90485fb342d85f22a479a7ceb5"
    },
    {
        "path": "a-marriage-of-sense-to-soul",
        "type": "directory",
        "md5": false
    },
    {
        "path": "/a-marriage-of-sense-to-soul/index.html",
        "type": "file",
        "md5": "5404922d97ebd156ca038d448b409d76"
    },
    {
        "path": "a-requiem",
        "type": "directory",
        "md5": false
    },
    {
        "path": "/a-requiem/index.html",
        "type": "file",
        "md5": "3e5f2b868d01a20cc225051eb72ff819"
    },
    {
        "path": "all-of-us",
        "type": "directory",
        "md5": false
    },
    {
        "path": "/all-of-us/index.html",
        "type": "file",
        "md5": "530f97b235d8143e735145edcb58c9e5"
    },
    {
        "path": "anahata-introduction-and-chapter-1",
        "type": "directory",
        "md5": false
    },
    {
        "path": "/anahata-introduction-and-chapter-1/index.html",
        "type": "file",
        "md5": "82168899bd7775dd1a7af578578b342b"
    },
    {
        "path": "apparitions",
        "type": "directory",
        "md5": false
    },
    {
        "path": "/apparitions/index.html",
        "type": "file",
        "md5": "4903204f3cb77d18a0dddcaca553d0dd"
    },
    {
        "path": "asana-ethics-and-evolution",
        "type": "directory",
        "md5": false
    },
    {
        "path": "/asana-ethics-and-evolution/index.html",
        "type": "file",
        "md5": "acc6c6870e0d2f6b310cd08de061b0c2"
    },
    {
        "path": "assets",
        "type": "directory",
        "md5": false
    },
    {
        "path": "assets/css",
        "type": "directory",
        "md5": false
    },
    {
        "path": "/assets/css/editor.css",
        "type": "file",
        "md5": "4202808df745f2ac7ab250606fa0d272"
    },
    {
        "path": "/assets/css/main.css",
        "type": "file",
        "md5": "fa238f48f9a2ab93b0c59a116e831bca"
    },
    {
        "path": "/assets/css/style.css",
        "type": "file",
        "md5": "11bee19e86e8eda2cf9a60efd975666d"
    },
    {
        "path": "assets/dynamic",
        "type": "directory",
        "md5": false
    },
    {
        "path": "assets/js",
        "type": "directory",
        "md5": false
    },
    {
        "path": "/assets/js/scripts.js",
        "type": "file",
        "md5": "e9e5c3efbaa696d1490988cf5b30e23b"
    },
    {
        "path": "/assets/js/scripts.min.js",
        "type": "file",
        "md5": "700105c316933a8202041b6415abb233"
    },
    {
        "path": "/assets/js/svg-fix.js",
        "type": "file",
        "md5": "9b7d020c55e2b4f77ab40c97f88f9ff4"
    },
    {
        "path": "/assets/js/svg-map.js",
        "type": "file",
        "md5": "ff4392540fcf4c3d3f5e03806e112816"
    },
    {
        "path": "assets/svg",
        "type": "directory",
        "md5": false
    },
    {
        "path": "/assets/svg/svg-map.svg",
        "type": "file",
        "md5": "cf04dfd5c3cc64e0be44692fe7d976a6"
    },
    {
        "path": "authors",
        "type": "directory",
        "md5": false
    },
    {
        "path": "authors/william-enckhausen",
        "type": "directory",
        "md5": false
    },
    {
        "path": "/authors/william-enckhausen/index.html",
        "type": "file",
        "md5": "0c01d99953217e94c720d08b0b4e3f77"
    },
    {
        "path": "collective-evolution",
        "type": "directory",
        "md5": false
    },
    {
        "path": "/collective-evolution/index.html",
        "type": "file",
        "md5": "3a9e034f7831e6f8f3726d28fd67c86d"
    },
    {
        "path": "contactfollow",
        "type": "directory",
        "md5": false
    },
    {
        "path": "/contactfollow/index.html",
        "type": "file",
        "md5": "e073b72af17e8b89004da780ce08a895"
    },
    {
        "path": "cool-kulkan",
        "type": "directory",
        "md5": false
    },
    {
        "path": "/cool-kulkan/index.html",
        "type": "file",
        "md5": "a5ce6dbd68f78789388a4847a9a32437"
    },
    {
        "path": "der-biermiester-des-reiches",
        "type": "directory",
        "md5": false
    },
    {
        "path": "/der-biermiester-des-reiches/index.html",
        "type": "file",
        "md5": "89fa5fe5c7ea0cc9a633ac324b8b84da"
    },
    {
        "path": "discernment-and-depression",
        "type": "directory",
        "md5": false
    },
    {
        "path": "/discernment-and-depression/index.html",
        "type": "file",
        "md5": "fc2fd006e0a77a1122f5e5fd4aef0805"
    },
    {
        "path": "dogma-dissonance-and-dissent-2",
        "type": "directory",
        "md5": false
    },
    {
        "path": "/dogma-dissonance-and-dissent-2/index.html",
        "type": "file",
        "md5": "9b3f4d6332a683f456583ea4d027a0e6"
    },
    {
        "path": "feed.json",
        "type": "file",
        "md5": "56cdb9bc34a081072d8084f4b99aff8f"
    },
    {
        "path": "feed.xml",
        "type": "file",
        "md5": "f66a2e3c8070c099dbfc6d8c7dc237eb"
    },
    {
        "path": "form-and-formless",
        "type": "directory",
        "md5": false
    },
    {
        "path": "/form-and-formless/index.html",
        "type": "file",
        "md5": "a47885a504265c3ff076fd5ddf90b88f"
    },
    {
        "path": "from-quetzalcoatl-to-cassanova",
        "type": "directory",
        "md5": false
    },
    {
        "path": "/from-quetzalcoatl-to-cassanova/index.html",
        "type": "file",
        "md5": "afa58510fe26dbf303756e3e58045c4e"
    },
    {
        "path": "gymnopedia-on-yerba-mate",
        "type": "directory",
        "md5": false
    },
    {
        "path": "/gymnopedia-on-yerba-mate/index.html",
        "type": "file",
        "md5": "773fafe5fe9c37bf09125b89c8e8ace5"
    },
    {
        "path": "hitler-killer-and-the-lizard-worshippers",
        "type": "directory",
        "md5": false
    },
    {
        "path": "/hitler-killer-and-the-lizard-worshippers/index.html",
        "type": "file",
        "md5": "cb31c82de0afa024558716e09d747cd8"
    },
    {
        "path": "index.html",
        "type": "file",
        "md5": "96bb411282d71fb785c903f7a2166ae4"
    },
    {
        "path": "joy-and-trauma",
        "type": "directory",
        "md5": false
    },
    {
        "path": "/joy-and-trauma/index.html",
        "type": "file",
        "md5": "ea25c9c01fe01b76ceae0033876be62c"
    },
    {
        "path": "light-and-dark-tantra",
        "type": "directory",
        "md5": false
    },
    {
        "path": "/light-and-dark-tantra/index.html",
        "type": "file",
        "md5": "4eabd5b52ee0b01109fde3e1c6813079"
    },
    {
        "path": "media",
        "type": "directory",
        "md5": false
    },
    {
        "path": "media/posts",
        "type": "directory",
        "md5": false
    },
    {
        "path": "media/posts/10",
        "type": "directory",
        "md5": false
    },
    {
        "path": "/media/posts/10/asana.jpg",
        "type": "file",
        "md5": "a2a0b6e63b180a1b17747197a04b3b84"
    },
    {
        "path": "/media/posts/10/hello-2.jpg",
        "type": "file",
        "md5": "4354e584e04332acf461e3391d66542c"
    },
    {
        "path": "media/posts/10/responsive",
        "type": "directory",
        "md5": false
    },
    {
        "path": "/media/posts/10/responsive/asana-2xl.jpg",
        "type": "file",
        "md5": "705810490a3aa19250229aff0c3d7b51"
    },
    {
        "path": "/media/posts/10/responsive/asana-lg.jpg",
        "type": "file",
        "md5": "705810490a3aa19250229aff0c3d7b51"
    },
    {
        "path": "/media/posts/10/responsive/asana-md.jpg",
        "type": "file",
        "md5": "705810490a3aa19250229aff0c3d7b51"
    },
    {
        "path": "/media/posts/10/responsive/asana-sm.jpg",
        "type": "file",
        "md5": "705810490a3aa19250229aff0c3d7b51"
    },
    {
        "path": "/media/posts/10/responsive/asana-xl.jpg",
        "type": "file",
        "md5": "705810490a3aa19250229aff0c3d7b51"
    },
    {
        "path": "/media/posts/10/responsive/asana-xs.jpg",
        "type": "file",
        "md5": "705810490a3aa19250229aff0c3d7b51"
    },
    {
        "path": "/media/posts/10/responsive/hello-2-2xl.jpg",
        "type": "file",
        "md5": "8614aecc410bec8ae6426a7cf56c3680"
    },
    {
        "path": "/media/posts/10/responsive/hello-2-lg.jpg",
        "type": "file",
        "md5": "8614aecc410bec8ae6426a7cf56c3680"
    },
    {
        "path": "/media/posts/10/responsive/hello-2-md.jpg",
        "type": "file",
        "md5": "8614aecc410bec8ae6426a7cf56c3680"
    },
    {
        "path": "/media/posts/10/responsive/hello-2-sm.jpg",
        "type": "file",
        "md5": "8614aecc410bec8ae6426a7cf56c3680"
    },
    {
        "path": "/media/posts/10/responsive/hello-2-xl.jpg",
        "type": "file",
        "md5": "8614aecc410bec8ae6426a7cf56c3680"
    },
    {
        "path": "/media/posts/10/responsive/hello-2-xs.jpg",
        "type": "file",
        "md5": "1e6d5c85c491a37a158f83dd8c0a716a"
    },
    {
        "path": "media/posts/11",
        "type": "directory",
        "md5": false
    },
    {
        "path": "/media/posts/11/capitol.jpg",
        "type": "file",
        "md5": "fe6618d11fa3c9091875c79b6bcd5cbb"
    },
    {
        "path": "media/posts/11/responsive",
        "type": "directory",
        "md5": false
    },
    {
        "path": "/media/posts/11/responsive/capitol-2xl.jpg",
        "type": "file",
        "md5": "001617759cd0a0e1a224d7c21159d292"
    },
    {
        "path": "/media/posts/11/responsive/capitol-lg.jpg",
        "type": "file",
        "md5": "001617759cd0a0e1a224d7c21159d292"
    },
    {
        "path": "/media/posts/11/responsive/capitol-md.jpg",
        "type": "file",
        "md5": "001617759cd0a0e1a224d7c21159d292"
    },
    {
        "path": "/media/posts/11/responsive/capitol-sm.jpg",
        "type": "file",
        "md5": "001617759cd0a0e1a224d7c21159d292"
    },
    {
        "path": "/media/posts/11/responsive/capitol-xl.jpg",
        "type": "file",
        "md5": "001617759cd0a0e1a224d7c21159d292"
    },
    {
        "path": "/media/posts/11/responsive/capitol-xs.jpg",
        "type": "file",
        "md5": "001617759cd0a0e1a224d7c21159d292"
    },
    {
        "path": "media/posts/12",
        "type": "directory",
        "md5": false
    },
    {
        "path": "media/posts/12/responsive",
        "type": "directory",
        "md5": false
    },
    {
        "path": "/media/posts/12/responsive/zapluna-2xl.jpg",
        "type": "file",
        "md5": "7973cd5579ae7359e66030f0c1b176fe"
    },
    {
        "path": "/media/posts/12/responsive/zapluna-lg.jpg",
        "type": "file",
        "md5": "7973cd5579ae7359e66030f0c1b176fe"
    },
    {
        "path": "/media/posts/12/responsive/zapluna-md.jpg",
        "type": "file",
        "md5": "7973cd5579ae7359e66030f0c1b176fe"
    },
    {
        "path": "/media/posts/12/responsive/zapluna-sm.jpg",
        "type": "file",
        "md5": "7973cd5579ae7359e66030f0c1b176fe"
    },
    {
        "path": "/media/posts/12/responsive/zapluna-xl.jpg",
        "type": "file",
        "md5": "7973cd5579ae7359e66030f0c1b176fe"
    },
    {
        "path": "/media/posts/12/responsive/zapluna-xs.jpg",
        "type": "file",
        "md5": "7973cd5579ae7359e66030f0c1b176fe"
    },
    {
        "path": "/media/posts/12/zapluna.jpg",
        "type": "file",
        "md5": "df1036122056f7ecab4c417a56acdc05"
    },
    {
        "path": "media/posts/13",
        "type": "directory",
        "md5": false
    },
    {
        "path": "media/posts/13/responsive",
        "type": "directory",
        "md5": false
    },
    {
        "path": "/media/posts/13/responsive/venados-2xl.jpg",
        "type": "file",
        "md5": "901294a2f4db831cd8969c135366fbd7"
    },
    {
        "path": "/media/posts/13/responsive/venados-lg.jpg",
        "type": "file",
        "md5": "901294a2f4db831cd8969c135366fbd7"
    },
    {
        "path": "/media/posts/13/responsive/venados-md.jpg",
        "type": "file",
        "md5": "901294a2f4db831cd8969c135366fbd7"
    },
    {
        "path": "/media/posts/13/responsive/venados-sm.jpg",
        "type": "file",
        "md5": "901294a2f4db831cd8969c135366fbd7"
    },
    {
        "path": "/media/posts/13/responsive/venados-xl.jpg",
        "type": "file",
        "md5": "901294a2f4db831cd8969c135366fbd7"
    },
    {
        "path": "/media/posts/13/responsive/venados-xs.jpg",
        "type": "file",
        "md5": "901294a2f4db831cd8969c135366fbd7"
    },
    {
        "path": "/media/posts/13/venados.jpg",
        "type": "file",
        "md5": "11bfdb8a7ffb2633d8b7ba70821684c6"
    },
    {
        "path": "media/posts/15",
        "type": "directory",
        "md5": false
    },
    {
        "path": "/media/posts/15/padmasambhava.jpg",
        "type": "file",
        "md5": "2e6202a0db180e99089f31077f76b826"
    },
    {
        "path": "media/posts/15/responsive",
        "type": "directory",
        "md5": false
    },
    {
        "path": "/media/posts/15/responsive/padmasambhava-2xl.jpg",
        "type": "file",
        "md5": "597445b7dca08cd97f3e78ba7e02f5bf"
    },
    {
        "path": "/media/posts/15/responsive/padmasambhava-lg.jpg",
        "type": "file",
        "md5": "597445b7dca08cd97f3e78ba7e02f5bf"
    },
    {
        "path": "/media/posts/15/responsive/padmasambhava-md.jpg",
        "type": "file",
        "md5": "597445b7dca08cd97f3e78ba7e02f5bf"
    },
    {
        "path": "/media/posts/15/responsive/padmasambhava-sm.jpg",
        "type": "file",
        "md5": "597445b7dca08cd97f3e78ba7e02f5bf"
    },
    {
        "path": "/media/posts/15/responsive/padmasambhava-xl.jpg",
        "type": "file",
        "md5": "597445b7dca08cd97f3e78ba7e02f5bf"
    },
    {
        "path": "/media/posts/15/responsive/padmasambhava-xs.jpg",
        "type": "file",
        "md5": "597445b7dca08cd97f3e78ba7e02f5bf"
    },
    {
        "path": "/media/posts/15/responsive/rolex-2xl.jpg",
        "type": "file",
        "md5": "fdbff61b8b20f67c9823e4319a6a90c3"
    },
    {
        "path": "/media/posts/15/responsive/rolex-lg.jpg",
        "type": "file",
        "md5": "fdbff61b8b20f67c9823e4319a6a90c3"
    },
    {
        "path": "/media/posts/15/responsive/rolex-md.jpg",
        "type": "file",
        "md5": "fdbff61b8b20f67c9823e4319a6a90c3"
    },
    {
        "path": "/media/posts/15/responsive/rolex-sm.jpg",
        "type": "file",
        "md5": "fdbff61b8b20f67c9823e4319a6a90c3"
    },
    {
        "path": "/media/posts/15/responsive/rolex-xl.jpg",
        "type": "file",
        "md5": "fdbff61b8b20f67c9823e4319a6a90c3"
    },
    {
        "path": "/media/posts/15/responsive/rolex-xs.jpg",
        "type": "file",
        "md5": "fdbff61b8b20f67c9823e4319a6a90c3"
    },
    {
        "path": "/media/posts/15/responsive/skunk-2xl.jpg",
        "type": "file",
        "md5": "c3bc85e0c75afd7d95eedf80b4fa0e50"
    },
    {
        "path": "/media/posts/15/responsive/skunk-lg.jpg",
        "type": "file",
        "md5": "c3bc85e0c75afd7d95eedf80b4fa0e50"
    },
    {
        "path": "/media/posts/15/responsive/skunk-md.jpg",
        "type": "file",
        "md5": "c3bc85e0c75afd7d95eedf80b4fa0e50"
    },
    {
        "path": "/media/posts/15/responsive/skunk-sm.jpg",
        "type": "file",
        "md5": "c3bc85e0c75afd7d95eedf80b4fa0e50"
    },
    {
        "path": "/media/posts/15/responsive/skunk-xl.jpg",
        "type": "file",
        "md5": "c3bc85e0c75afd7d95eedf80b4fa0e50"
    },
    {
        "path": "/media/posts/15/responsive/skunk-xs.jpg",
        "type": "file",
        "md5": "c3bc85e0c75afd7d95eedf80b4fa0e50"
    },
    {
        "path": "/media/posts/15/rolex.jpg",
        "type": "file",
        "md5": "c2b8ece5d84450968575deb3eb0fcb7a"
    },
    {
        "path": "/media/posts/15/skunk.jpg",
        "type": "file",
        "md5": "7ce5e04cab392e3bdad798a2c2a6de05"
    },
    {
        "path": "media/posts/20",
        "type": "directory",
        "md5": false
    },
    {
        "path": "media/posts/20/responsive",
        "type": "directory",
        "md5": false
    },
    {
        "path": "/media/posts/20/responsive/rublev-2xl.jpg",
        "type": "file",
        "md5": "01099141db40494377f3cbc1b3121dc1"
    },
    {
        "path": "/media/posts/20/responsive/rublev-lg.jpg",
        "type": "file",
        "md5": "01099141db40494377f3cbc1b3121dc1"
    },
    {
        "path": "/media/posts/20/responsive/rublev-md.jpg",
        "type": "file",
        "md5": "01099141db40494377f3cbc1b3121dc1"
    },
    {
        "path": "/media/posts/20/responsive/rublev-sm.jpg",
        "type": "file",
        "md5": "cccd37b3e235b66184094eb566a59bde"
    },
    {
        "path": "/media/posts/20/responsive/rublev-xl.jpg",
        "type": "file",
        "md5": "01099141db40494377f3cbc1b3121dc1"
    },
    {
        "path": "/media/posts/20/responsive/rublev-xs.jpg",
        "type": "file",
        "md5": "7cccbd10bfba740ac9042757639fb8ae"
    },
    {
        "path": "/media/posts/20/rublev.jpg",
        "type": "file",
        "md5": "8648a1a63238c508577c6aba823d339f"
    },
    {
        "path": "media/posts/26",
        "type": "directory",
        "md5": false
    },
    {
        "path": "/media/posts/26/coffee.jpg",
        "type": "file",
        "md5": "e7ec5d5d51a2771d83c46207203e2757"
    },
    {
        "path": "media/posts/26/responsive",
        "type": "directory",
        "md5": false
    },
    {
        "path": "/media/posts/26/responsive/coffee-2xl.jpg",
        "type": "file",
        "md5": "481e47173b730a71343c774db6c89a4a"
    },
    {
        "path": "/media/posts/26/responsive/coffee-lg.jpg",
        "type": "file",
        "md5": "481e47173b730a71343c774db6c89a4a"
    },
    {
        "path": "/media/posts/26/responsive/coffee-md.jpg",
        "type": "file",
        "md5": "481e47173b730a71343c774db6c89a4a"
    },
    {
        "path": "/media/posts/26/responsive/coffee-sm.jpg",
        "type": "file",
        "md5": "481e47173b730a71343c774db6c89a4a"
    },
    {
        "path": "/media/posts/26/responsive/coffee-xl.jpg",
        "type": "file",
        "md5": "481e47173b730a71343c774db6c89a4a"
    },
    {
        "path": "/media/posts/26/responsive/coffee-xs.jpg",
        "type": "file",
        "md5": "481e47173b730a71343c774db6c89a4a"
    },
    {
        "path": "media/posts/29",
        "type": "directory",
        "md5": false
    },
    {
        "path": "/media/posts/29/kurmakasana.jpg",
        "type": "file",
        "md5": "49e6d19c4336bdb5f213045bcf25c38d"
    },
    {
        "path": "/media/posts/29/quetzalcoatl-2.jpg",
        "type": "file",
        "md5": "08b5a58ce270cc92318bf69ee87f0955"
    },
    {
        "path": "media/posts/29/responsive",
        "type": "directory",
        "md5": false
    },
    {
        "path": "/media/posts/29/responsive/kurmakasana-2xl.jpg",
        "type": "file",
        "md5": "d5bf6a3ace7ef7299542ea1835a2ca82"
    },
    {
        "path": "/media/posts/29/responsive/kurmakasana-lg.jpg",
        "type": "file",
        "md5": "d5bf6a3ace7ef7299542ea1835a2ca82"
    },
    {
        "path": "/media/posts/29/responsive/kurmakasana-md.jpg",
        "type": "file",
        "md5": "d5bf6a3ace7ef7299542ea1835a2ca82"
    },
    {
        "path": "/media/posts/29/responsive/kurmakasana-sm.jpg",
        "type": "file",
        "md5": "d5bf6a3ace7ef7299542ea1835a2ca82"
    },
    {
        "path": "/media/posts/29/responsive/kurmakasana-xl.jpg",
        "type": "file",
        "md5": "d5bf6a3ace7ef7299542ea1835a2ca82"
    },
    {
        "path": "/media/posts/29/responsive/kurmakasana-xs.jpg",
        "type": "file",
        "md5": "d5bf6a3ace7ef7299542ea1835a2ca82"
    },
    {
        "path": "/media/posts/29/responsive/quetzalcoatl-2-2xl.jpg",
        "type": "file",
        "md5": "d35b4173d2e056509171bcef4a25c1f5"
    },
    {
        "path": "/media/posts/29/responsive/quetzalcoatl-2-lg.jpg",
        "type": "file",
        "md5": "d35b4173d2e056509171bcef4a25c1f5"
    },
    {
        "path": "/media/posts/29/responsive/quetzalcoatl-2-md.jpg",
        "type": "file",
        "md5": "d35b4173d2e056509171bcef4a25c1f5"
    },
    {
        "path": "/media/posts/29/responsive/quetzalcoatl-2-sm.jpg",
        "type": "file",
        "md5": "d35b4173d2e056509171bcef4a25c1f5"
    },
    {
        "path": "/media/posts/29/responsive/quetzalcoatl-2-xl.jpg",
        "type": "file",
        "md5": "d35b4173d2e056509171bcef4a25c1f5"
    },
    {
        "path": "/media/posts/29/responsive/quetzalcoatl-2-xs.jpg",
        "type": "file",
        "md5": "d35b4173d2e056509171bcef4a25c1f5"
    },
    {
        "path": "media/posts/31",
        "type": "directory",
        "md5": false
    },
    {
        "path": "/media/posts/31/ceiba.jpg",
        "type": "file",
        "md5": "1fceaf8f981dbd0a57ba6e0f32413f1a"
    },
    {
        "path": "media/posts/31/responsive",
        "type": "directory",
        "md5": false
    },
    {
        "path": "/media/posts/31/responsive/ceiba-2xl.jpg",
        "type": "file",
        "md5": "2e66c36386e49148a5dcbb3d95427ca2"
    },
    {
        "path": "/media/posts/31/responsive/ceiba-lg.jpg",
        "type": "file",
        "md5": "2e66c36386e49148a5dcbb3d95427ca2"
    },
    {
        "path": "/media/posts/31/responsive/ceiba-md.jpg",
        "type": "file",
        "md5": "2e66c36386e49148a5dcbb3d95427ca2"
    },
    {
        "path": "/media/posts/31/responsive/ceiba-sm.jpg",
        "type": "file",
        "md5": "2e66c36386e49148a5dcbb3d95427ca2"
    },
    {
        "path": "/media/posts/31/responsive/ceiba-xl.jpg",
        "type": "file",
        "md5": "2e66c36386e49148a5dcbb3d95427ca2"
    },
    {
        "path": "/media/posts/31/responsive/ceiba-xs.jpg",
        "type": "file",
        "md5": "2e66c36386e49148a5dcbb3d95427ca2"
    },
    {
        "path": "media/posts/36",
        "type": "directory",
        "md5": false
    },
    {
        "path": "/media/posts/36/ernst.jpg",
        "type": "file",
        "md5": "d9c9a228caca3525bc40e075d24fc2b9"
    },
    {
        "path": "media/posts/36/responsive",
        "type": "directory",
        "md5": false
    },
    {
        "path": "/media/posts/36/responsive/ernst-2xl.jpg",
        "type": "file",
        "md5": "e6eae499261714d29b3ec5af87dca4b6"
    },
    {
        "path": "/media/posts/36/responsive/ernst-lg.jpg",
        "type": "file",
        "md5": "60732f1b8f0d1edf76708983323c1964"
    },
    {
        "path": "/media/posts/36/responsive/ernst-md.jpg",
        "type": "file",
        "md5": "c05bb8e6fe4589a574fc8561cbc2dbf7"
    },
    {
        "path": "/media/posts/36/responsive/ernst-sm.jpg",
        "type": "file",
        "md5": "ecaf473bba445bb2e21392251818e4ff"
    },
    {
        "path": "/media/posts/36/responsive/ernst-xl.jpg",
        "type": "file",
        "md5": "e6eae499261714d29b3ec5af87dca4b6"
    },
    {
        "path": "/media/posts/36/responsive/ernst-xs.jpg",
        "type": "file",
        "md5": "b2516a9c9b3476d49ee3820df2746e8e"
    },
    {
        "path": "media/posts/43",
        "type": "directory",
        "md5": false
    },
    {
        "path": "/media/posts/43/9.jpg",
        "type": "file",
        "md5": "da7d3786a32c3a549ce8866ed21b5ef1"
    },
    {
        "path": "media/posts/43/responsive",
        "type": "directory",
        "md5": false
    },
    {
        "path": "/media/posts/43/responsive/9-2xl.jpg",
        "type": "file",
        "md5": "b979fda68baafd8b3efde8e0ec1b0c9b"
    },
    {
        "path": "/media/posts/43/responsive/9-lg.jpg",
        "type": "file",
        "md5": "b979fda68baafd8b3efde8e0ec1b0c9b"
    },
    {
        "path": "/media/posts/43/responsive/9-md.jpg",
        "type": "file",
        "md5": "b979fda68baafd8b3efde8e0ec1b0c9b"
    },
    {
        "path": "/media/posts/43/responsive/9-sm.jpg",
        "type": "file",
        "md5": "dc7c8f07ba8e305ea89cfffdfacbba78"
    },
    {
        "path": "/media/posts/43/responsive/9-xl.jpg",
        "type": "file",
        "md5": "b979fda68baafd8b3efde8e0ec1b0c9b"
    },
    {
        "path": "/media/posts/43/responsive/9-xs.jpg",
        "type": "file",
        "md5": "ecf08dc3bacfa7d82500c3e94ae4fc76"
    },
    {
        "path": "media/posts/48",
        "type": "directory",
        "md5": false
    },
    {
        "path": "/media/posts/48/acharyas.jpg",
        "type": "file",
        "md5": "8624b6442f000cfb29fbc74948b0ad8a"
    },
    {
        "path": "/media/posts/48/chidghananda.jpg",
        "type": "file",
        "md5": "ea83944cde411901d752363963c02a48"
    },
    {
        "path": "/media/posts/48/quetzal.jpg",
        "type": "file",
        "md5": "e4612f49582e0af09785f530a0b1e587"
    },
    {
        "path": "media/posts/48/responsive",
        "type": "directory",
        "md5": false
    },
    {
        "path": "/media/posts/48/responsive/acharyas-2xl.jpg",
        "type": "file",
        "md5": "f87a2d389c532d1a097545c17b30b174"
    },
    {
        "path": "/media/posts/48/responsive/acharyas-lg.jpg",
        "type": "file",
        "md5": "f87a2d389c532d1a097545c17b30b174"
    },
    {
        "path": "/media/posts/48/responsive/acharyas-md.jpg",
        "type": "file",
        "md5": "f87a2d389c532d1a097545c17b30b174"
    },
    {
        "path": "/media/posts/48/responsive/acharyas-sm.jpg",
        "type": "file",
        "md5": "f87a2d389c532d1a097545c17b30b174"
    },
    {
        "path": "/media/posts/48/responsive/acharyas-xl.jpg",
        "type": "file",
        "md5": "f87a2d389c532d1a097545c17b30b174"
    },
    {
        "path": "/media/posts/48/responsive/acharyas-xs.jpg",
        "type": "file",
        "md5": "faea2a9ff9cdb0cf7fcc3ac30f24a87d"
    },
    {
        "path": "/media/posts/48/responsive/chidghananda-2xl.jpg",
        "type": "file",
        "md5": "d2f3764fb31f6d04510ad27b88d65e4a"
    },
    {
        "path": "/media/posts/48/responsive/chidghananda-lg.jpg",
        "type": "file",
        "md5": "d2f3764fb31f6d04510ad27b88d65e4a"
    },
    {
        "path": "/media/posts/48/responsive/chidghananda-md.jpg",
        "type": "file",
        "md5": "d2f3764fb31f6d04510ad27b88d65e4a"
    },
    {
        "path": "/media/posts/48/responsive/chidghananda-sm.jpg",
        "type": "file",
        "md5": "d2f3764fb31f6d04510ad27b88d65e4a"
    },
    {
        "path": "/media/posts/48/responsive/chidghananda-xl.jpg",
        "type": "file",
        "md5": "d2f3764fb31f6d04510ad27b88d65e4a"
    },
    {
        "path": "/media/posts/48/responsive/chidghananda-xs.jpg",
        "type": "file",
        "md5": "d2f3764fb31f6d04510ad27b88d65e4a"
    },
    {
        "path": "/media/posts/48/responsive/quetzal-2xl.jpg",
        "type": "file",
        "md5": "70e1eb47be422c1267efae4c17c8b2e4"
    },
    {
        "path": "/media/posts/48/responsive/quetzal-lg.jpg",
        "type": "file",
        "md5": "70e1eb47be422c1267efae4c17c8b2e4"
    },
    {
        "path": "/media/posts/48/responsive/quetzal-md.jpg",
        "type": "file",
        "md5": "70e1eb47be422c1267efae4c17c8b2e4"
    },
    {
        "path": "/media/posts/48/responsive/quetzal-sm.jpg",
        "type": "file",
        "md5": "7fe779d9ba2bc09f39b2949433a1902f"
    },
    {
        "path": "/media/posts/48/responsive/quetzal-xl.jpg",
        "type": "file",
        "md5": "70e1eb47be422c1267efae4c17c8b2e4"
    },
    {
        "path": "/media/posts/48/responsive/quetzal-xs.jpg",
        "type": "file",
        "md5": "68e2ea85b5c8431a6c8c74feb0d21dfd"
    },
    {
        "path": "media/posts/53",
        "type": "directory",
        "md5": false
    },
    {
        "path": "media/posts/53/responsive",
        "type": "directory",
        "md5": false
    },
    {
        "path": "/media/posts/53/responsive/white-trash-2-2xl.jpg",
        "type": "file",
        "md5": "6dd7a8dedefb778053534cd217f1aa78"
    },
    {
        "path": "/media/posts/53/responsive/white-trash-2-lg.jpg",
        "type": "file",
        "md5": "6dd7a8dedefb778053534cd217f1aa78"
    },
    {
        "path": "/media/posts/53/responsive/white-trash-2-md.jpg",
        "type": "file",
        "md5": "6dd7a8dedefb778053534cd217f1aa78"
    },
    {
        "path": "/media/posts/53/responsive/white-trash-2-sm.jpg",
        "type": "file",
        "md5": "9d61d1e5c043567fbe9f8a6c97bc0e8a"
    },
    {
        "path": "/media/posts/53/responsive/white-trash-2-xl.jpg",
        "type": "file",
        "md5": "6dd7a8dedefb778053534cd217f1aa78"
    },
    {
        "path": "/media/posts/53/responsive/white-trash-2-xs.jpg",
        "type": "file",
        "md5": "446f29c370327c9426190c0612bc2da6"
    },
    {
        "path": "/media/posts/53/responsive/white-trash-2xl.jpg",
        "type": "file",
        "md5": "6dd7a8dedefb778053534cd217f1aa78"
    },
    {
        "path": "/media/posts/53/responsive/white-trash-lg.jpg",
        "type": "file",
        "md5": "6dd7a8dedefb778053534cd217f1aa78"
    },
    {
        "path": "/media/posts/53/responsive/white-trash-md.jpg",
        "type": "file",
        "md5": "6dd7a8dedefb778053534cd217f1aa78"
    },
    {
        "path": "/media/posts/53/responsive/white-trash-sm.jpg",
        "type": "file",
        "md5": "9d61d1e5c043567fbe9f8a6c97bc0e8a"
    },
    {
        "path": "/media/posts/53/responsive/white-trash-xl.jpg",
        "type": "file",
        "md5": "6dd7a8dedefb778053534cd217f1aa78"
    },
    {
        "path": "/media/posts/53/responsive/white-trash-xs.jpg",
        "type": "file",
        "md5": "446f29c370327c9426190c0612bc2da6"
    },
    {
        "path": "/media/posts/53/white-trash-2.jpg",
        "type": "file",
        "md5": "a16c525747a5b75d799ff42f4d41ee81"
    },
    {
        "path": "/media/posts/53/white-trash.jpg",
        "type": "file",
        "md5": "a16c525747a5b75d799ff42f4d41ee81"
    },
    {
        "path": "media/posts/57",
        "type": "directory",
        "md5": false
    },
    {
        "path": "/media/posts/57/napalmgirl.jpg",
        "type": "file",
        "md5": "42e45d3ac525cc38fd2551a35b943816"
    },
    {
        "path": "media/posts/57/responsive",
        "type": "directory",
        "md5": false
    },
    {
        "path": "/media/posts/57/responsive/napalmgirl-2xl.jpg",
        "type": "file",
        "md5": "033162e9c0469dec54ae2068eff2a7b1"
    },
    {
        "path": "/media/posts/57/responsive/napalmgirl-lg.jpg",
        "type": "file",
        "md5": "033162e9c0469dec54ae2068eff2a7b1"
    },
    {
        "path": "/media/posts/57/responsive/napalmgirl-md.jpg",
        "type": "file",
        "md5": "033162e9c0469dec54ae2068eff2a7b1"
    },
    {
        "path": "/media/posts/57/responsive/napalmgirl-sm.jpg",
        "type": "file",
        "md5": "033162e9c0469dec54ae2068eff2a7b1"
    },
    {
        "path": "/media/posts/57/responsive/napalmgirl-xl.jpg",
        "type": "file",
        "md5": "033162e9c0469dec54ae2068eff2a7b1"
    },
    {
        "path": "/media/posts/57/responsive/napalmgirl-xs.jpg",
        "type": "file",
        "md5": "033162e9c0469dec54ae2068eff2a7b1"
    },
    {
        "path": "media/posts/6",
        "type": "directory",
        "md5": false
    },
    {
        "path": "/media/posts/6/acharyas.jpg",
        "type": "file",
        "md5": "8624b6442f000cfb29fbc74948b0ad8a"
    },
    {
        "path": "media/posts/6/responsive",
        "type": "directory",
        "md5": false
    },
    {
        "path": "/media/posts/6/responsive/acharyas-2xl.jpg",
        "type": "file",
        "md5": "f87a2d389c532d1a097545c17b30b174"
    },
    {
        "path": "/media/posts/6/responsive/acharyas-lg.jpg",
        "type": "file",
        "md5": "f87a2d389c532d1a097545c17b30b174"
    },
    {
        "path": "/media/posts/6/responsive/acharyas-md.jpg",
        "type": "file",
        "md5": "f87a2d389c532d1a097545c17b30b174"
    },
    {
        "path": "/media/posts/6/responsive/acharyas-sm.jpg",
        "type": "file",
        "md5": "f87a2d389c532d1a097545c17b30b174"
    },
    {
        "path": "/media/posts/6/responsive/acharyas-xl.jpg",
        "type": "file",
        "md5": "f87a2d389c532d1a097545c17b30b174"
    },
    {
        "path": "/media/posts/6/responsive/acharyas-xs.jpg",
        "type": "file",
        "md5": "faea2a9ff9cdb0cf7fcc3ac30f24a87d"
    },
    {
        "path": "media/posts/66",
        "type": "directory",
        "md5": false
    },
    {
        "path": "media/posts/66/responsive",
        "type": "directory",
        "md5": false
    },
    {
        "path": "/media/posts/66/responsive/Trump-Christ-2xl-2xl.webp",
        "type": "file",
        "md5": "8c67ec53e31c79895861913cd099b1f2"
    },
    {
        "path": "/media/posts/66/responsive/Trump-Christ-2xl-lg.webp",
        "type": "file",
        "md5": "8c67ec53e31c79895861913cd099b1f2"
    },
    {
        "path": "/media/posts/66/responsive/Trump-Christ-2xl-md.webp",
        "type": "file",
        "md5": "8c67ec53e31c79895861913cd099b1f2"
    },
    {
        "path": "/media/posts/66/responsive/Trump-Christ-2xl-sm.webp",
        "type": "file",
        "md5": "8c67ec53e31c79895861913cd099b1f2"
    },
    {
        "path": "/media/posts/66/responsive/Trump-Christ-2xl-xl.webp",
        "type": "file",
        "md5": "8c67ec53e31c79895861913cd099b1f2"
    },
    {
        "path": "/media/posts/66/responsive/Trump-Christ-2xl-xs.webp",
        "type": "file",
        "md5": "5d99b1f6d828a2e6ecb7d3264e10a1e5"
    },
    {
        "path": "/media/posts/66/Trump-Christ-2xl.webp",
        "type": "file",
        "md5": "afd853bf232c66d6c22d9737aeca366f"
    },
    {
        "path": "media/posts/7",
        "type": "directory",
        "md5": false
    },
    {
        "path": "/media/posts/7/anandamurti.jpg",
        "type": "file",
        "md5": "4cff02c7ec97708a6325f3ed7186c442"
    },
    {
        "path": "media/posts/7/responsive",
        "type": "directory",
        "md5": false
    },
    {
        "path": "/media/posts/7/responsive/anandamurti-2xl.jpg",
        "type": "file",
        "md5": "2c1db6df068f51d436be00426acc1493"
    },
    {
        "path": "/media/posts/7/responsive/anandamurti-lg.jpg",
        "type": "file",
        "md5": "2c1db6df068f51d436be00426acc1493"
    },
    {
        "path": "/media/posts/7/responsive/anandamurti-md.jpg",
        "type": "file",
        "md5": "2c1db6df068f51d436be00426acc1493"
    },
    {
        "path": "/media/posts/7/responsive/anandamurti-sm.jpg",
        "type": "file",
        "md5": "2c1db6df068f51d436be00426acc1493"
    },
    {
        "path": "/media/posts/7/responsive/anandamurti-xl.jpg",
        "type": "file",
        "md5": "2c1db6df068f51d436be00426acc1493"
    },
    {
        "path": "/media/posts/7/responsive/anandamurti-xs.jpg",
        "type": "file",
        "md5": "2c1db6df068f51d436be00426acc1493"
    },
    {
        "path": "media/website",
        "type": "directory",
        "md5": false
    },
    {
        "path": "/media/website/ceiba.jpg",
        "type": "file",
        "md5": "f67fc68995411d82a3b2f0f2e158db5b"
    },
    {
        "path": "/media/website/quetzal.jpg",
        "type": "file",
        "md5": "e4612f49582e0af09785f530a0b1e587"
    },
    {
        "path": "media/website/responsive",
        "type": "directory",
        "md5": false
    },
    {
        "path": "/media/website/responsive/ceiba-2xl.jpg",
        "type": "file",
        "md5": "8cac33f3a46fbe2e8b077330f5b818bd"
    },
    {
        "path": "/media/website/responsive/ceiba-lg.jpg",
        "type": "file",
        "md5": "f3fd10d04e1e09dd74917da37e0d6379"
    },
    {
        "path": "/media/website/responsive/ceiba-md.jpg",
        "type": "file",
        "md5": "7482a2d4e1acd30960a05a358459c6f9"
    },
    {
        "path": "/media/website/responsive/ceiba-sm.jpg",
        "type": "file",
        "md5": "5deab22e0a1c5d012aebe8f6a656d301"
    },
    {
        "path": "/media/website/responsive/ceiba-xl.jpg",
        "type": "file",
        "md5": "01088207a5cf365f495af4d0d78ee1aa"
    },
    {
        "path": "/media/website/responsive/ceiba-xs.jpg",
        "type": "file",
        "md5": "ca26a57f74719fc88e8517537d6bf6c4"
    },
    {
        "path": "/media/website/responsive/quetzal-2xl.jpg",
        "type": "file",
        "md5": "70e1eb47be422c1267efae4c17c8b2e4"
    },
    {
        "path": "/media/website/responsive/quetzal-lg.jpg",
        "type": "file",
        "md5": "70e1eb47be422c1267efae4c17c8b2e4"
    },
    {
        "path": "/media/website/responsive/quetzal-md.jpg",
        "type": "file",
        "md5": "70e1eb47be422c1267efae4c17c8b2e4"
    },
    {
        "path": "/media/website/responsive/quetzal-sm.jpg",
        "type": "file",
        "md5": "7fe779d9ba2bc09f39b2949433a1902f"
    },
    {
        "path": "/media/website/responsive/quetzal-xl.jpg",
        "type": "file",
        "md5": "70e1eb47be422c1267efae4c17c8b2e4"
    },
    {
        "path": "/media/website/responsive/quetzal-xs.jpg",
        "type": "file",
        "md5": "68e2ea85b5c8431a6c8c74feb0d21dfd"
    },
    {
        "path": "personalities",
        "type": "directory",
        "md5": false
    },
    {
        "path": "/personalities/index.html",
        "type": "file",
        "md5": "06884c7c6076789f40d62be51ca62c51"
    },
    {
        "path": "pleasures-habits-and-addictions",
        "type": "directory",
        "md5": false
    },
    {
        "path": "/pleasures-habits-and-addictions/index.html",
        "type": "file",
        "md5": "cc95f47d335fe7691131e6ae80e1e40d"
    },
    {
        "path": "psorax",
        "type": "directory",
        "md5": false
    },
    {
        "path": "/psorax/index.html",
        "type": "file",
        "md5": "58b61ab073905f431b5b071ce86bdff0"
    },
    {
        "path": "quetzal-bill-to-bonzai-baba",
        "type": "directory",
        "md5": false
    },
    {
        "path": "/quetzal-bill-to-bonzai-baba/index.html",
        "type": "file",
        "md5": "3697a41deac8fb2afa490d729e05d57b"
    },
    {
        "path": "recreating",
        "type": "directory",
        "md5": false
    },
    {
        "path": "/recreating/index.html",
        "type": "file",
        "md5": "035eee3f209140ba7b8a53c3b03a0744"
    },
    {
        "path": "redemption",
        "type": "directory",
        "md5": false
    },
    {
        "path": "/redemption/index.html",
        "type": "file",
        "md5": "5fc5931f18cb86e28672fd9e4c8e93ab"
    },
    {
        "path": "robots.txt",
        "type": "file",
        "md5": "f2006949a4e85aa0139dc41998d90597"
    },
    {
        "path": "search-index.json",
        "type": "file",
        "md5": "ae7d30c9c1a8cf51c6a4fc8b0e536911"
    },
    {
        "path": "search.html",
        "type": "file",
        "md5": "5956805497db17c07ef0dc96318b3797"
    },
    {
        "path": "sitemap.xml",
        "type": "file",
        "md5": "f72e523da1161c9f1867be5683289152"
    },
    {
        "path": "sitemap.xsl",
        "type": "file",
        "md5": "03c2f9a7fdcc46ff05c435907614a0b8"
    },
    {
        "path": "stories-of-quetzal",
        "type": "directory",
        "md5": false
    },
    {
        "path": "/stories-of-quetzal/index.html",
        "type": "file",
        "md5": "8479942d01834fe83c568f6569dc3bd5"
    },
    {
        "path": "tags",
        "type": "directory",
        "md5": false
    },
    {
        "path": "/tags/index.html",
        "type": "file",
        "md5": "d2d367ddc8494494f37ecf73c761e9dc"
    },
    {
        "path": "the-breaking-point-and-the-possessed",
        "type": "directory",
        "md5": false
    },
    {
        "path": "/the-breaking-point-and-the-possessed/index.html",
        "type": "file",
        "md5": "7628a7fa5f2cfe4255d31d676c4c138b"
    },
    {
        "path": "the-debate",
        "type": "directory",
        "md5": false
    },
    {
        "path": "/the-debate/index.html",
        "type": "file",
        "md5": "4b55e587818108841420e58e5b0472fb"
    },
    {
        "path": "the-divine-cactus",
        "type": "directory",
        "md5": false
    },
    {
        "path": "/the-divine-cactus/index.html",
        "type": "file",
        "md5": "a82061a3b7ff35d4a533ebb4ec7a4351"
    },
    {
        "path": "the-elite-pseudoculture",
        "type": "directory",
        "md5": false
    },
    {
        "path": "/the-elite-pseudoculture/index.html",
        "type": "file",
        "md5": "47b518bbfbddf6222637080204e8cec4"
    },
    {
        "path": "the-indigenous-revolution",
        "type": "directory",
        "md5": false
    },
    {
        "path": "/the-indigenous-revolution/index.html",
        "type": "file",
        "md5": "c77e408ac946c14a8cf588e7716cd30c"
    },
    {
        "path": "the-infinite-eye",
        "type": "directory",
        "md5": false
    },
    {
        "path": "/the-infinite-eye/index.html",
        "type": "file",
        "md5": "751007282b1944631cd547082c258807"
    },
    {
        "path": "the-inward-mirror",
        "type": "directory",
        "md5": false
    },
    {
        "path": "/the-inward-mirror/index.html",
        "type": "file",
        "md5": "a58c74261d388e33e7f3c967eced76ae"
    },
    {
        "path": "the-liberation-of-desire",
        "type": "directory",
        "md5": false
    },
    {
        "path": "/the-liberation-of-desire/index.html",
        "type": "file",
        "md5": "01538c706c5eb0ceab6f8108ac5e1436"
    },
    {
        "path": "the-net",
        "type": "directory",
        "md5": false
    },
    {
        "path": "/the-net/index.html",
        "type": "file",
        "md5": "fd8cac01a1784a4ee0f501a855e1448b"
    },
    {
        "path": "the-perennial-philosophy",
        "type": "directory",
        "md5": false
    },
    {
        "path": "/the-perennial-philosophy/index.html",
        "type": "file",
        "md5": "1b007a7ee188c3f03af12fb5e470b683"
    },
    {
        "path": "the-shadow-of-the-guru",
        "type": "directory",
        "md5": false
    },
    {
        "path": "/the-shadow-of-the-guru/index.html",
        "type": "file",
        "md5": "f0494e038446614e90ad3df1389be807"
    },
    {
        "path": "the-timeless-tattoo",
        "type": "directory",
        "md5": false
    },
    {
        "path": "/the-timeless-tattoo/index.html",
        "type": "file",
        "md5": "d23d92bd34f6d545a8b686c16ceed3d6"
    },
    {
        "path": "the-tree-tantra",
        "type": "directory",
        "md5": false
    },
    {
        "path": "/the-tree-tantra/index.html",
        "type": "file",
        "md5": "562d980c4e0440bf84ef6ecf96c6d1a4"
    },
    {
        "path": "the-way",
        "type": "directory",
        "md5": false
    },
    {
        "path": "/the-way/index.html",
        "type": "file",
        "md5": "72204906ec902e9f3f38bb3c033075aa"
    },
    {
        "path": "universal-tantra",
        "type": "directory",
        "md5": false
    },
    {
        "path": "/universal-tantra/index.html",
        "type": "file",
        "md5": "f353ead5e69e5d011db925c13cbb84b4"
    },
    {
        "path": "white-trash-2",
        "type": "directory",
        "md5": false
    },
    {
        "path": "/white-trash-2/index.html",
        "type": "file",
        "md5": "dda0241998d982466fa15793ef9ce7af"
    },
    {
        "path": "why-is-this-evil-upon-us",
        "type": "directory",
        "md5": false
    },
    {
        "path": "/why-is-this-evil-upon-us/index.html",
        "type": "file",
        "md5": "752654d6f40d3d3dc0f061d53c78cc27"
    },
    {
        "path": "william-enckhausen",
        "type": "directory",
        "md5": false
    },
    {
        "path": "/william-enckhausen/index.html",
        "type": "file",
        "md5": "8b5f550349f01ba30bb6fbcc57c92839"
    },
    {
        "path": "works",
        "type": "directory",
        "md5": false
    },
    {
        "path": "/works/index.html",
        "type": "file",
        "md5": "f5cdcb0a00fe37bcb05ab8f7b6967cfa"
    }
]